CHANGELOG
INSTALL
LICENSE
MANIFEST.in
README
doTests
setup.py
docs/Makefile
docs/createDocs
docs/make.bat
docs/source/changelog.rst
docs/source/conf.py
docs/source/configure.rst
docs/source/index.rst
docs/source/installation.rst
docs/source/screenshots.rst
docs/source/static/oyProjectManager_Projects_and_Users_relation.mm
docs/source/static/oyProjectManager_data_schema.mm
docs/source/static/oyProjectManager_environments.mm
docs/source/static/oyProjectManager_system_config.mm
docs/source/static/oyProjectManager_version_paths_relative_or_absolute.mm
docs/source/static/oyProjectManager_with_SQLAlchemy.mm
docs/source/static/oyProjectManager_with_mayaEnv.mm
docs/source/static/.backup/oyProjectManager_data_schema.mm.1.autosave
docs/source/static/.backup/oyProjectManager_data_schema.mm.2.autosave
docs/source/static/.backup/oyProjectManager_data_schema.mm.3.autosave
docs/source/static/.backup/oyProjectManager_environments.mm.1.autosave
docs/source/static/.backup/oyProjectManager_version_paths_relative_or_absolute.mm.1.autosave
docs/source/static/.backup/oyProjectManager_version_paths_relative_or_absolute.mm.2.autosave
docs/source/static/.backup/oyProjectManager_version_paths_relative_or_absolute.mm.3.autosave
docs/source/static/.backup/oyProjectManager_version_paths_relative_or_absolute.mm.4.autosave
docs/source/static/.backup/oyProjectManager_version_paths_relative_or_absolute.mm.5.autosave
docs/source/static/.backup/oyProjectManager_version_paths_relative_or_absolute.mm.6.autosave
docs/source/static/.backup/oyProjectManager_version_paths_relative_or_absolute.mm.7.autosave
docs/source/static/.backup/oyProjectManager_version_paths_relative_or_absolute.mm.8.autosave
docs/source/static/.backup/oyProjectManager_version_paths_relative_or_absolute.mm.9.autosave
docs/source/static/images/screenshots/screenshot_pm_001.png
docs/source/static/images/screenshots/screenshot_pm_002.png
docs/source/static/images/screenshots/screenshot_pm_003.png
oyProjectManager.egg-info/PKG-INFO
oyProjectManager.egg-info/SOURCES.txt
oyProjectManager.egg-info/dependency_links.txt
oyProjectManager.egg-info/requires.txt
oyProjectManager.egg-info/top_level.txt
