Metadata-Version: 1.1
Name: oyProjectManager
Version: 0.2.5.3
Summary: A Simple Asset Management System for Animation and VFX Studios
Home-page: http://code.google.com/p/oyprojectmanager/
Author: Erkan Ozgur Yilmaz
Author-email: eoyilmaz@gmail.com
License: http://www.opensource.org/licenses/bsd-license.php
Keywords: production,asset,management,vfx,animation,mayahoudini,nuke,xsi,blender,vue
Platform: any
Classifier: Programming Language :: Python
Classifier: License :: OSI Approved :: BSD License
Classifier: Operating System :: OS Independent
Classifier: Development Status :: 5 - Production/Stable
Classifier: Intended Audience :: Developers
Classifier: Intended Audience :: End Users/Desktop
Classifier: Topic :: Database
Classifier: Topic :: Software Development
Classifier: Topic :: Utilities
Classifier: Topic :: Office/Business :: Scheduling
Requires: sqlalchemy
Requires: jinja2
